promptdown-1.1.6.dist-info/METADATA
promptdown-1.1.6.dist-info/WHEEL
promptdown-1.1.6.dist-info/entry_points.txt
promptdown-1.1.6.dist-info/licenses/LICENSE
promptdown/__init__.py
promptdown/converters.py
promptdown/promptdown.py
promptdown/py.typed
promptdown/types.py
promptdown-1.1.6.dist-info/RECORD
