Metadata-Version: 2.1
Name: promptdown
Version: 1.1.6
Summary: A package for loading promptdown files, which are a special type of markdown file for defining structured LLM prompts
Author-Email: "B.T. Franklin" <brandon.franklin@gmail.com>
License: MIT License
Classifier: Programming Language :: Python :: 3
Classifier: Programming Language :: Python :: 3 :: Only
Classifier: Programming Language :: Python :: 3.10
Classifier: Programming Language :: Python :: 3.11
Classifier: Programming Language :: Python :: 3.12
Classifier: Programming Language :: Python :: 3.13
Classifier: Programming Language :: Python :: 3.14
Classifier: Typing :: Typed
Classifier: License :: OSI Approved :: MIT License
Classifier: Operating System :: OS Independent
Classifier: Intended Audience :: Developers
Classifier: Topic :: File Formats
Classifier: Topic :: Software Development :: Libraries :: Python Modules
Classifier: Topic :: Text Processing :: Markup :: Markdown
Project-URL: Homepage, https://github.com/btfranklin/promptdown
Project-URL: Issues, https://github.com/btfranklin/promptdown/issues
Project-URL: Changelog, https://github.com/btfranklin/promptdown/releases
Project-URL: Repository, https://github.com/btfranklin/promptdown.git
Requires-Python: >=3.10
